odoo10_addon_sale_promotion_rule-10.0.2.1.1-nspkg.pth
odoo/addons/sale_promotion_rule/README.rst
odoo/addons/sale_promotion_rule/__init__.py
odoo/addons/sale_promotion_rule/__manifest__.py
odoo/addons/sale_promotion_rule/i18n/ca.po
odoo/addons/sale_promotion_rule/i18n/fr.po
odoo/addons/sale_promotion_rule/i18n/sale_promotion_rule.pot
odoo/addons/sale_promotion_rule/migrations/10.0.2.0.0/post-migration.py
odoo/addons/sale_promotion_rule/models/__init__.py
odoo/addons/sale_promotion_rule/models/sale_order.py
odoo/addons/sale_promotion_rule/models/sale_order_line.py
odoo/addons/sale_promotion_rule/models/sale_promotion_rule.py
odoo/addons/sale_promotion_rule/readme/CONTRIBUTORS.rst
odoo/addons/sale_promotion_rule/readme/DESCRIPTION.rst
odoo/addons/sale_promotion_rule/readme/ROADMAP.rst
odoo/addons/sale_promotion_rule/security/ir.model.access.csv
odoo/addons/sale_promotion_rule/static/description/icon.png
odoo/addons/sale_promotion_rule/static/description/index.html
odoo/addons/sale_promotion_rule/static/description/promotion_rule.png
odoo/addons/sale_promotion_rule/tests/__init__.py
odoo/addons/sale_promotion_rule/tests/test_promotion.py
odoo/addons/sale_promotion_rule/views/sale_order.xml
odoo/addons/sale_promotion_rule/views/sale_promotion_rule.xml
odoo/addons/sale_promotion_rule/wizards/__init__.py
odoo/addons/sale_promotion_rule/wizards/sale_order_add_coupon.py
odoo/addons/sale_promotion_rule/wizards/sale_order_add_coupon.xml
odoo10_addon_sale_promotion_rule-10.0.2.1.1.dist-info/METADATA
odoo10_addon_sale_promotion_rule-10.0.2.1.1.dist-info/WHEEL
odoo10_addon_sale_promotion_rule-10.0.2.1.1.dist-info/namespace_packages.txt
odoo10_addon_sale_promotion_rule-10.0.2.1.1.dist-info/top_level.txt
odoo10_addon_sale_promotion_rule-10.0.2.1.1.dist-info/RECORD
