Metadata-Version: 2.1
Name: odoo10-addon-sale-promotion-rule
Version: 10.0.2.1.1
Summary: Module to manage promotion rule on sale order
Home-page: https://github.com/OCA/sale-workflow
Author: Akretion, ACSONE SA/NV, Odoo Community Association (OCA)
Author-email: support@odoo-community.org
License: AGPL-3
Platform: UNKNOWN
Classifier: Programming Language :: Python
Classifier: Framework :: Odoo
Classifier: License :: OSI Approved :: GNU Affero General Public License v3
Classifier: Development Status :: 4 - Beta
Requires-Python: ~=2.7
Requires-Dist: odoo (<10.1dev,>=10.0)
